Workbook

Sheet Resumo
A1: Olist: resumo executivo
A2: Marketplace brasileiro | pedidos entregues, compra de jan/2017 a ago/2018 | dados reais públicos (Kaggle). Todos os números abaixo são fórmulas ligadas às demais abas.
A4: Indicadores-chave
A5: Indicador | B5: Valor | C5: Leitura
A6: Receita (itens, R$) | B6: =KPIs_Mensais!E25 -> 13181027 | C6: Receita de produtos, sem frete e sem margem (a base não tem custos).
A7: Pedidos entregues | B7: =KPIs_Mensais!D25 -> 96211 | C7: Escopo: status entregue, 20 meses completos.
A8: Receita por Pedido (R$) | B8: =KPIs_Mensais!F25 -> 137.00125 | C8: Estável ao longo do período: o crescimento vem de volume.
A9: Receita YoY % (jan-ago/2018 vs jan-ago/2017) | B9: =SUMIFS(KPIs_Mensais!E5:E24,KPIs_Mensais!B5:B24,2018,KPIs_Mensais!C5:C24,"<=8")/SUMIFS(KPIs_Mensais!E5:E24,KPIs_Mensais!B5:B24,2017,KPIs_Mensais!C5:C24,"<=8")-1 -> 1.4113015 | C9: Mesmos oito meses de cada ano, para comparação justa.
A10: % Atraso | B10: =KPIs_Mensais!I25 -> 0.081307236 | C10: Atraso medido contra a data estimada informada ao cliente.
A11: Nota Média (1 a 5) | B11: =KPIs_Mensais!L25 -> 4.1563285 | C11: Média geral; veja a queda por faixa de atraso abaixo.
A12: Taxa de Recompra % | B12: =Clientes_RFM!B15 -> 0.029955748 | C12: Clientes com 2 ou mais pedidos: retenção é o maior espaço de crescimento.
A13: Receita Top 20% Vendedores % | B13: =Vendedores!B13 -> 0.82198948 | C13: Receita concentrada em poucos vendedores.
A15: Principais achados
A16: Achado | B16: Valor | C16: Indicador
A17: Atraso derruba a nota | B17: =Atraso_vs_Nota!E5 -> 4.2949308 | C17: Nota média dos pedidos entregues no prazo
B18: =Atraso_vs_Nota!E8 -> 1.7279503 | C18: Nota média dos pedidos com atraso acima de 7 dias
A19: Poucos pedidos atrasados concentram a insatisfação | B19: =Atraso_vs_Nota!B13 -> 0.079499791 | C19: % dos pedidos com atraso, entre os que têm avaliação (difere levemente do indicador geral)
B20: =Atraso_vs_Nota!B14 -> 0.33832188 | C20: % das notas baixas (1 a 2) vindas desses pedidos
A21: Nordeste sofre mais com a entrega | B21: =Logistica_UF!D37 -> 0.14364947 | C21: % de atraso no Nordeste
B22: =Logistica_UF!D39 -> 0.074659194 | C22: % de atraso no Sudeste (referência)
A23: Prazo apertado para a rota atrasa muito mais | B23: =Modelo_Risco!D5 -> 0.30385757 | C23: Taxa de atraso quando o prazo prometido é igual ou menor que o típico da rota
B24: =Modelo_Risco!D9 -> 0.043864598 | C24: Taxa de atraso quando há folga de mais de 15 dias
A25: Dá para antecipar parte dos atrasos na compra | B25: =Modelo_Risco!B16 -> 0.2684 | C25: % dos atrasos capturados ao sinalizar os 10% de pedidos de maior risco
A26: Black Friday exige capacidade | B26: =INDEX(KPIs_Mensais!M5:M24,MATCH("2017-11",KPIs_Mensais!A5:A24,0)) -> 0.52374694 | C26: Variação da receita de nov/2017 sobre out/2017
A28: Gráficos

Sheet Recomendacoes
A1: Recomendações priorizadas
A2: Prioridade = julgamento do analista a partir da evidência. Valores são fórmulas ligadas às abas de dados (verde).
A4: # | B4: Prioridade | C4: Área | D4: Ação recomendada | E4: Evidência | F4: Métrica-chave (valor atual | referência) | G4: Valor atual | H4: Referência
A5: 1 | B5: Alta | C5: Operações / Atendimento | D5: Tratar atrasos acima de 3 dias como incidente: aviso proativo ao cliente, atendimento prioritário e compensação. | E5: A nota despenca nos atrasos mais longos, onde a maioria das avaliações é 1 ou 2. | F5: Nota média com atraso > 7 dias | nota média no prazo | G5: =Atraso_vs_Nota!E8 -> 1.7279503 | H5: =Atraso_vs_Nota!E5 -> 4.2949308
A6: 2 | B6: Alta | C6: Logística | D6: Atacar a logística do Nordeste (AL, MA, PI, CE, SE, BA): revisar transportadoras e rotas; avaliar centros de distribuição. | E6: Maiores taxas de atraso, prazos mais longos e frete mais pesado. | F6: % de atraso no Nordeste | Sudeste | G6: =Logistica_UF!D37 -> 0.14364947 | H6: =Logistica_UF!D39 -> 0.074659194
A7: 3 | B7: Alta | C7: Logística / Produto | D7: Calibrar o prazo prometido pela rota: onde o prazo é igual ou menor que o típico, estender a promessa ou reforçar a operação. Testar em A/B o efeito na conversão. | E7: Prazo apertado para a rota atrasa muito mais; o prazo bruto sozinho não é bom preditor. | F7: Atraso com folga <= 0 | folga > 15 dias | G7: =Modelo_Risco!D5 -> 0.30385757 | H7: =Modelo_Risco!D9 -> 0.043864598
A8: 4 | B8: Alta | C8: Operações / Dados | D8: Triagem proativa: sinalizar o top 10% de risco para aviso ao cliente, priorização no despacho e acompanhamento. | E8: Os pedidos de maior risco concentram boa parte dos atrasos. | F8: Atrasos capturados no top 10% | sorteio aleatório | G8: =Modelo_Risco!B16 -> 0.2684 | H8: =Modelo_Risco!A16 -> 0.1
A9: 5 | B9: Média | C9: Comercial / CRM | D9: Reativar clientes inativos de alto valor e fazer onboarding dos novos de alto valor. | E9: A recompra é muito baixa e não é explicada por atraso ou nota baixa; o gargalo é relacionamento. | F9: % da receita nos inativos de alto valor | taxa de recompra | G9: =Clientes_RFM!B16 -> 0.28828989 | H9: =Clientes_RFM!B15 -> 0.029955748
A10: 6 | B10: Média | C10: Comercial | D10: Reduzir a dependência de poucos vendedores: programa de desenvolvimento do 2º quintil e monitoramento de risco nos maiores. | E10: A receita está concentrada nos maiores vendedores. | F10: % da receita dos 20% maiores | 20% proporcional | G10: =Vendedores!B13 -> 0.82198948 | H10: =Vendedores!D5 -> 0.2
A11: 7 | B11: Média | C11: Operações | D11: Planejar capacidade para picos sazonais (Black Friday). | E11: Pico expressivo de receita e de atraso em nov/2017. | F11: Receita nov/17 sobre out/17 | média mensal de variação | G11: =INDEX(KPIs_Mensais!M5:M24,MATCH("2017-11",KPIs_Mensais!A5:A24,0)) -> 0.52374694 | H11: =AVERAGE(KPIs_Mensais!M6:M24) -> 0.14694224
A12: 8 | B12: Média | C12: Dados | D12: Retreinar o modelo todo mês e monitorar o AUC; investigar se cair perto de 0,6. | E12: A política de prazos mudou em 2018 e relações do passado deixaram de valer (concept drift). | F12: AUC médio | AUC do pior mês | G12: =Modelo_Risco!B22 -> 0.694 | H12: =Modelo_Risco!D22 -> 0.617

Sheet KPIs_Mensais
A1: KPIs mensais
A2: Pedidos entregues, compra entre jan/2017 e ago/2018. Azul = dado de entrada; preto = fórmula.
A4: Ano-Mês | B4: Ano | C4: Mês | D4: Pedidos | E4: Receita (R$) | F4: Receita por Pedido (R$) | G4: Entregues c/ data | H4: Atrasados | I4: % Atraso | J4: Avaliações | K4: Soma das notas | L4: Nota Média | M4: Receita MoM %
A5: 2017-01 | B5: 2017 | C5: 1 | D5: 750 | E5: 111798.36 | F5: =E5/D5 -> 149.06448 | G5: 750 | H5: 23 | I5: =H5/G5 -> 0.030666667 | J5: 741 | K5: 3111 | L5: =K5/J5 -> 4.1983806
A6: 2017-02 | B6: 2017 | C6: 2 | D6: 1653 | E6: 234223.4 | F6: =E6/D6 -> 141.69595 | G6: 1653 | H6: 53 | I6: =H6/G6 -> 0.032062916 | J6: 1643 | K6: 6906 | L6: =K6/J6 -> 4.2032867 | M6: =E6/E5-1 -> 1.0950522
A7: 2017-03 | B7: 2017 | C7: 3 | D7: 2546 | E7: 359198.85 | F7: =E7/D7 -> 141.0836 | G7: 2546 | H7: 142 | I7: =H7/G7 -> 0.055773763 | J7: 2527 | K7: 10580 | L7: =K7/J7 -> 4.1867827 | M7: =E7/E6-1 -> 0.53357372
A8: 2017-04 | B8: 2017 | C8: 4 | D8: 2303 | E8: 340669.68 | F8: =E8/D8 -> 147.92431 | G8: 2303 | H8: 181 | I8: =H8/G8 -> 0.078593139 | J8: 2290 | K8: 9470 | L8: =K8/J8 -> 4.1353712 | M8: =E8/E7-1 -> -0.051584714
A9: 2017-05 | B9: 2017 | C9: 5 | D9: 3546 | E9: 489338.25 | F9: =E9/D9 -> 137.99725 | G9: 3545 | H9: 128 | I9: =H9/G9 -> 0.036107193 | J9: 3518 | K9: 14904 | L9: =K9/J9 -> 4.236498 | M9: =E9/E8-1 -> 0.43640094
A10: 2017-06 | B10: 2017 | C10: 6 | D10: 3135 | E10: 421923.37 | F10: =E10/D10 -> 134.58481 | G10: 3135 | H10: 121 | I10: =H10/G10 -> 0.038596491 | J10: 3111 | K10: 13137 | L10: =K10/J10 -> 4.222758 | M10: =E10/E9-1 -> -0.13776744
A11: 2017-07 | B11: 2017 | C11: 7 | D11: 3872 | E11: 481604.52 | F11: =E11/D11 -> 124.38133 | G11: 3872 | H11: 133 | I11: =H11/G11 -> 0.034349174 | J11: 3842 | K11: 16365 | L11: =K11/J11 -> 4.2595003 | M11: =E11/E10-1 -> 0.14145021
A12: 2017-08 | B12: 2017 | C12: 8 | D12: 4193 | E12: 554699.7 | F12: =E12/D12 -> 132.29184 | G12: 4193 | H12: 139 | I12: =H12/G12 -> 0.033150489 | J12: 4165 | K12: 17963 | L12: =K12/J12 -> 4.3128451 | M12: =E12/E11-1 -> 0.15177428
A13: 2017-09 | B13: 2017 | C13: 9 | D13: 4150 | E13: 607399.67 | F13: =E13/D13 -> 146.36137 | G13: 4150 | H13: 216 | I13: =H13/G13 -> 0.052048193 | J13: 4118 | K13: 17575 | L13: =K13/J13 -> 4.2678485 | M13: =E13/E12-1 -> 0.095006307
A14: 2017-10 | B14: 2017 | C14: 10 | D14: 4478 | E14: 648247.65 | F14: =E14/D14 -> 144.76276 | G14: 4478 | H14: 237 | I14: =H14/G14 -> 0.052925413 | J14: 4446 | K14: 18695 | L14: =K14/J14 -> 4.2049033 | M14: =E14/E13-1 -> 0.06725058
A15: 2017-11 | B15: 2017 | C15: 11 | D15: 7289 | E15: 987765.37 | F15: =E15/D15 -> 135.51452 | G15: 7288 | H15: 1043 | I15: =H15/G15 -> 0.14311196 | J15: 7238 | K15: 28872 | L15: =K15/J15 -> 3.9889472 | M15: =E15/E14-1 -> 0.52374694
A16: 2017-12 | B16: 2017 | C16: 12 | D16: 5513 | E16: 726033.19 | F16: =E16/D16 -> 131.69476 | G16: 5513 | H16: 462 | I16: =H16/G16 -> 0.083801923 | J16: 5461 | K16: 22327 | L16: =K16/J16 -> 4.0884453 | M16: =E16/E15-1 -> -0.26497404
A17: 2018-01 | B17: 2018 | C17: 1 | D17: 7069 | E17: 924645 | F17: =E17/D17 -> 130.8028 | G17: 7069 | H17: 464 | I17: =H17/G17 -> 0.065638704 | J17: 7013 | K17: 28813 | L17: =K17/J17 -> 4.1085128 | M17: =E17/E16-1 -> 0.27355748
... A24: 2018-08 | B24: 2018 | C24: 8 | D24: 6351 | E24: 838576.64 | F24: =E24/D24 -> 132.03852 | G24: 6351 | H24: 660 | I24: =H24/G24 -> 0.10392064 | J24: 6330 | K24: 27284 | L24: =K24/J24 -> 4.3102686 | M24: =E24/E23-1 -> -0.033846077
A25: Total | D25: =SUM(D5:D24) -> 96211 | E25: =SUM(E5:E24) -> 13181027 | F25: =E25/D25 -> 137.00125 | G25: =SUM(G5:G24) -> 96203 | H25: =SUM(H5:H24) -> 7822 | I25: =H25/G25 -> 0.081307236 | J25: =SUM(J5:J24) -> 95568 | K25: =SUM(K5:K24) -> 397212 | L25: =K25/J25 -> 4.1563285

Sheet Logistica_UF
A1: Logística por estado e região
A2: Entrega x prazo estimado. UFs com menos de 200 pedidos têm amostra pequena. Azul = dado de entrada; preto = fórmula.
A4: UF | B4: Região | C4: Pedidos | D4: % Atraso | E4: Entrega Média (dias) | F4: Frete % Receita | G4: Nota Média | H4: Amostra | J4: Receita (R$) | K4: Frete (R$) | L4: Entregues c/ data | M4: Atrasados | N4: Soma dias entrega | O4: Avaliações | P4: Soma das notas
A5: AL | B5: Nordeste | C5: 396 | D5: =M5/L5 -> 0.23989899 | E5: =N5/L5 -> 24.524242 | F5: =K5/J5 -> 0.19402345 | G5: =P5/O5 -> 3.8473282 | H5: =IF(C5<200,"amostra pequena","ok") -> ok | J5: 78805.73 | K5: 15290.16 | L5: 396 | M5: 95 | N5: 9711.6 | O5: 393 | P5: 1512
A6: MA | B6: Nordeste | C6: 713 | D6: =M6/L6 -> 0.19635344 | E6: =N6/L6 -> 21.536606 | F6: =K6/J6 -> 0.26223764 | G6: =P6/O6 -> 3.8293371 | H6: =IF(C6<200,"amostra pequena","ok") -> ok | J6: 116305.12 | K6: 30499.58 | L6: 713 | M6: 140 | N6: 15355.6 | O6: 709 | P6: 2715
A7: PI | B7: Nordeste | C7: 475 | D7: =M7/L7 -> 0.16 | E7: =N7/L7 -> 19.441263 | F7: =K7/J7 -> 0.24163837 | G7: =P7/O7 -> 3.993617 | H7: =IF(C7<200,"amostra pequena","ok") -> ok | J7: 84511 | K7: 20421.1 | L7: 475 | M7: 76 | N7: 9234.6 | O7: 470 | P7: 1877
A8: CE | B8: Nordeste | C8: 1273 | D8: =M8/L8 -> 0.15396701 | E8: =N8/L8 -> 21.237785 | F8: =K8/J8 -> 0.21293925 | G8: =P8/O8 -> 3.9400158 | H8: =IF(C8<200,"amostra pequena","ok") -> ok | J8: 218107.7 | K8: 46443.69 | L8: 1273 | M8: 196 | N8: 27035.7 | O8: 1267 | P8: 4992
A9: SE | B9: Nordeste | C9: 332 | D9: =M9/L9 -> 0.15361446 | E9: =N9/L9 -> 21.437651 | F9: =K9/J9 -> 0.24257907 | G9: =P9/O9 -> 3.9003021 | H9: =IF(C9<200,"amostra pequena","ok") -> ok | J9: 56288.74 | K9: 13654.47 | L9: 332 | M9: 51 | N9: 7117.3 | O9: 331 | P9: 1291
A10: BA | B10: Nordeste | C10: 3253 | D10: =M10/L10 -> 0.14048571 | E10: =N10/L10 -> 19.333508 | F10: =K10/J10 -> 0.19758723 | G10: =P10/O10 -> 3.9302542 | H10: =IF(C10<200,"amostra pequena","ok") -> ok | J10: 493339.26 | K10: 97477.54 | L10: 3253 | M10: 457 | N10: 62891.9 | O10: 3226 | P10: 12679
A11: RJ | B11: Sudeste | C11: 12310 | D11: =M11/L11 -> 0.13517465 | E11: =N11/L11 -> 15.296799 | F11: =K11/J11 -> 0.16838991 | G11: =P11/O11 -> 3.9654946 | H11: =IF(C11<200,"amostra pequena","ok") -> ok | J11: 1751433.9 | K11: 294923.79 | L11: 12310 | M11: 1664 | N11: 188303.6 | O11: 12172 | P11: 48268
A12: TO | B12: Norte | C12: 274 | D12: =M12/L12 -> 0.12773723 | E12: =N12/L12 -> 17.656569 | F12: =K12/J12 -> 0.2397574 | G12: =P12/O12 -> 4.1538462 | H12: =IF(C12<200,"amostra pequena","ok") -> ok | J12: 48402.51 | K12: 11604.86 | L12: 274 | M12: 35 | N12: 4837.9 | O12: 273 | P12: 1134
A13: RR | B13: Norte | C13: 40 | D13: =M13/L13 -> 0.125 | E13: =N13/L13 -> 29.905 | F13: =K13/J13 -> 0.27825506 | G13: =P13/O13 -> 3.9 | H13: =IF(C13<200,"amostra pequena","ok") -> amostra pequena | J13: 7017.77 | K13: 1952.73 | L13: 40 | M13: 5 | N13: 1196.2 | O13: 40 | P13: 156
A14: PA | B14: Norte | C14: 942 | D14: =M14/L14 -> 0.12420382 | E14: =N14/L14 -> 23.757749 | F14: =K14/J14 -> 0.21546225 | G14: =P14/O14 -> 3.9128095 | H14: =IF(C14<200,"amostra pequena","ok") -> ok | J14: 173382.99 | K14: 37357.49 | L14: 942 | M14: 117 | N14: 22379.8 | O14: 929 | P14: 3635
A15: ES | B15: Sudeste | C15: 1992 | D15: =M15/L15 -> 0.12248996 | E15: =N15/L15 -> 15.774247 | F15: =K15/J15 -> 0.1825446 | G15: =P15/O15 -> 4.0788403 | H15: =IF(C15<200,"amostra pequena","ok") -> ok | J15: 267783.66 | K15: 48882.46 | L15: 1992 | M15: 244 | N15: 31422.3 | O15: 1966 | P15: 8019
A16: MS | B16: Centro-Oeste | C16: 701 | D16: =M16/L16 -> 0.11554922 | E16: =N16/L16 -> 15.618402 | F16: =K16/J16 -> 0.16406121 | G16: =P16/O16 -> 4.1616595 | H16: =IF(C16<200,"amostra pequena","ok") -> ok | J16: 115429.97 | K16: 18937.58 | L16: 701 | M16: 81 | N16: 10948.5 | O16: 699 | P16: 2909
... A31: RO | B31: Norte | C31: 243 | D31: =M31/L31 -> 0.028806584 | E31: =N31/L31 -> 19.374897 | F31: =K31/J31 -> 0.24699121 | G31: =P31/O31 -> 4.1652893 | H31: =IF(C31<200,"amostra pequena","ok") -> ok | J31: 45682.76 | K31: 11283.24 | L31: 243 | M31: 7 | N31: 4708.1 | O31: 242 | P31: 1008
A32: Total | C32: =SUM(C5:C31) -> 96211 | D32: =M32/L32 -> 0.081307236 | E32: =N32/L32 -> 12.538411 | F32: =K32/J32 -> 0.16630668 | G32: =P32/O32 -> 4.1563285 | J32: =SUM(J5:J31) -> 13181027 | K32: =SUM(K5:K31) -> 2192092.9 | L32: =SUM(L5:L31) -> 96203 | M32: =SUM(M5:M31) -> 7822 | N32: =SUM(N5:N31) -> 1206232.8 | O32: =SUM(O5:O31) -> 95568 | P32: =SUM(P5:P31) -> 397212
A34: Por região
A35: Região | C35: Pedidos | D35: % Atraso | E35: Entrega Média (dias) | F35: Frete % Receita | G35: Nota Média
A36: Norte | C36: =SUMIFS(C$5:C$31,B$5:B$31,$A36) -> 1791 | D36: =SUMIFS(M$5:M$31,B$5:B$31,$A36)/SUMIFS(L$5:L$31,B$5:B$31,$A36) -> 0.098269123 | E36: =SUMIFS(N$5:N$31,B$5:B$31,$A36)/SUMIFS(L$5:L$31,B$5:B$31,$A36) -> 22.58928 | F36: =SUMIFS(K$5:K$31,B$5:B$31,$A36)/SUMIFS(J$5:J$31,B$5:B$31,$A36) -> 0.22715092 | G36: =SUMIFS(P$5:P$31,B$5:B$31,$A36)/SUMIFS(O$5:O$31,B$5:B$31,$A36) -> 4.0310034
A37: Nordeste | C37: =SUMIFS(C$5:C$31,B$5:B$31,$A37) -> 9015 | D37: =SUMIFS(M$5:M$31,B$5:B$31,$A37)/SUMIFS(L$5:L$31,B$5:B$31,$A37) -> 0.14364947 | E37: =SUMIFS(N$5:N$31,B$5:B$31,$A37)/SUMIFS(L$5:L$31,B$5:B$31,$A37) -> 19.986356 | F37: =SUMIFS(K$5:K$31,B$5:B$31,$A37)/SUMIFS(J$5:J$31,B$5:B$31,$A37) -> 0.21734409 | G37: =SUMIFS(P$5:P$31,B$5:B$31,$A37)/SUMIFS(O$5:O$31,B$5:B$31,$A37) -> 3.9682575
A38: Centro-Oeste | C38: =SUMIFS(C$5:C$31,B$5:B$31,$A38) -> 5610 | D38: =SUMIFS(M$5:M$31,B$5:B$31,$A38)/SUMIFS(L$5:L$31,B$5:B$31,$A38) -> 0.079857398 | E38: =SUMIFS(N$5:N$31,B$5:B$31,$A38)/SUMIFS(L$5:L$31,B$5:B$31,$A38) -> 15.011783 | F38: =SUMIFS(K$5:K$31,B$5:B$31,$A38)/SUMIFS(J$5:J$31,B$5:B$31,$A38) -> 0.17587726 | G38: =SUMIFS(P$5:P$31,B$5:B$31,$A38)/SUMIFS(O$5:O$31,B$5:B$31,$A38) -> 4.1286738
A39: Sudeste | C39: =SUMIFS(C$5:C$31,B$5:B$31,$A39) -> 66027 | D39: =SUMIFS(M$5:M$31,B$5:B$31,$A39)/SUMIFS(L$5:L$31,B$5:B$31,$A39) -> 0.074659194 | E39: =SUMIFS(N$5:N$31,B$5:B$31,$A39)/SUMIFS(L$5:L$31,B$5:B$31,$A39) -> 10.729617 | F39: =SUMIFS(K$5:K$31,B$5:B$31,$A39)/SUMIFS(J$5:J$31,B$5:B$31,$A39) -> 0.15191517 | G39: =SUMIFS(P$5:P$31,B$5:B$31,$A39)/SUMIFS(O$5:O$31,B$5:B$31,$A39) -> 4.1802736
A40: Sul | C40: =SUMIFS(C$5:C$31,B$5:B$31,$A40) -> 13768 | D40: =SUMIFS(M$5:M$31,B$5:B$31,$A40)/SUMIFS(L$5:L$31,B$5:B$31,$A40) -> 0.070748892 | E40: =SUMIFS(N$5:N$31,B$5:B$31,$A40)/SUMIFS(L$5:L$31,B$5:B$31,$A40) -> 14.019975 | F40: =SUMIFS(K$5:K$31,B$5:B$31,$A40)/SUMIFS(J$5:J$31,B$5:B$31,$A40) -> 0.17687871 | G40: =SUMIFS(P$5:P$31,B$5:B$31,$A40)/SUMIFS(O$5:O$31,B$5:B$31,$A40) -> 4.1920438

Sheet Atraso_vs_Nota
A1: Atraso x satisfação do cliente
A2: Pedidos entregues com data de entrega e avaliação. Azul = dado de entrada; preto = fórmula.
A4: Faixa de atraso | B4: Pedidos | C4: Soma das notas | D4: Notas baixas (1 a 2) | E4: Nota Média | F4: % Notas Baixas | G4: % dos pedidos | H4: % das notas baixas totais
A5: 1. No prazo | B5: 87963 | C5: 377795 | D5: 8091 | E5: =C5/B5 -> 4.2949308 | F5: =D5/B5 -> 0.091981856 | G5: =B5/B$9 -> 0.92050021 | H5: =D5/D$9 -> 0.66167812
A6: 2. Atraso 1-3 dias | B6: 2590 | C6: 9703 | D6: 510 | E6: =C6/B6 -> 3.746332 | F6: =D6/B6 -> 0.1969112 | G6: =B6/B$9 -> 0.027103391 | H6: =D6/D$9 -> 0.041707556
A7: 3. Atraso 4-7 dias | B7: 1787 | C7: 4114 | D7: 1102 | E7: =C7/B7 -> 2.3021824 | F7: =D7/B7 -> 0.61667599 | G7: =B7/B$9 -> 0.018700293 | H7: =D7/D$9 -> 0.090121034
A8: 4. Atraso > 7 dias | B8: 3220 | C8: 5564 | D8: 2525 | E8: =C8/B8 -> 1.7279503 | F8: =D8/B8 -> 0.78416149 | G8: =B8/B$9 -> 0.033696107 | H8: =D8/D$9 -> 0.20649329
A9: Total | B9: =SUM(B5:B8) -> 95560 | C9: =SUM(C5:C8) -> 397176 | D9: =SUM(D5:D8) -> 12228 | E9: =C9/B9 -> 4.1562997 | F9: =D9/B9 -> 0.12796149 | G9: =B9/B$9 -> 1 | H9: =D9/D$9 -> 1
A12: Indicadores derivados
A13: % dos pedidos que chegaram com atraso | B13: =SUM(B6:B8)/B9 -> 0.079499791
A14: % das notas baixas vindas de pedidos atrasados | B14: =SUM(D6:D8)/D9 -> 0.33832188
A15: Queda de nota: no prazo vs atraso > 7 dias | B15: =E5-E8 -> 2.5669805

Sheet Categorias
A1: Receita por categoria: Top 10
A2: Receita de itens (pedidos entregues, jan/2017 a ago/2018). Azul = dado de entrada; verde = vínculo com outra aba; preto = fórmula.
A4: Categoria | B4: Receita (R$) | C4: % da receita | D4: % acumulado
A5: Beleza e Saúde | B5: 1229557.5 | C5: =B5/B$16 -> 0.093282374 | D5: =SUM(C$5:C5) -> 0.093282374
A6: Relógios e Presentes | B6: 1163465.9 | C6: =B6/B$16 -> 0.088268228 | D6: =SUM(C$5:C6) -> 0.1815506
A7: Cama, Mesa e Banho | B7: 1022955.8 | C7: =B7/B$16 -> 0.077608199 | D7: =SUM(C$5:C7) -> 0.2591588
A8: Esporte e Lazer | B8: 952840.4 | C8: =B8/B$16 -> 0.072288782 | D8: =SUM(C$5:C8) -> 0.33144758
A9: Informática e Acessórios | B9: 888055.59 | C9: =B9/B$16 -> 0.067373778 | D9: =SUM(C$5:C9) -> 0.39882136
A10: Móveis e Decoração | B10: 706237.17 | C10: =B10/B$16 -> 0.053579828 | D10: =SUM(C$5:C10) -> 0.45240119
A11: Utilidades Domésticas | B11: 614341.62 | C11: =B11/B$16 -> 0.046608023 | D11: =SUM(C$5:C11) -> 0.49900921
A12: Gadgets e Novidades | B12: 609158 | C12: =B12/B$16 -> 0.04621476 | D12: =SUM(C$5:C12) -> 0.54522397
A13: Automotivo | B13: 577838.39 | C13: =B13/B$16 -> 0.043838647 | D13: =SUM(C$5:C13) -> 0.58906262
A14: Ferramentas de Jardim | B14: 469135.4 | C14: =B14/B$16 -> 0.035591718 | D14: =SUM(C$5:C14) -> 0.62465434
A15: Demais categorias | B15: =B16-SUM(B5:B14) -> 4947441.4 | C15: =B15/B$16 -> 0.37534566 | D15: =SUM(C$5:C15) -> 1
A16: Total (= receita da aba KPIs_Mensais) | B16: =KPIs_Mensais!E25 -> 13181027 | C16: =B16/B$16 -> 1
A18: Categorias no top 10 respondem por | B18: =D14 -> 0.62465434

Sheet Clientes_RFM
A1: Clientes: recompra e segmentação RFM
A2: Segmentos por regras de negócio (recência, valor, recorrência) sobre o período inteiro. Azul = dado de entrada; preto = fórmula.
A4: Segmento | B4: Clientes | C4: Receita (R$) | D4: % Clientes | E4: % Receita | F4: Receita por cliente (R$)
A5: Novos de alto valor | B5: 14443 | C5: 3857426.5 | D5: =B5/B$11 -> 0.1551276 | E5: =C5/C$11 -> 0.29264992 | F5: =C5/B5 -> 267.07932
A6: Inativos de alto valor | B6: 13748 | C6: 3799956.8 | D6: =B6/B$11 -> 0.14766283 | E6: =C6/C$11 -> 0.28828989 | F6: =C6/B6 -> 276.4007
A7: Intermediários | B7: 18019 | C7: 2344440.3 | D7: =B7/B$11 -> 0.19353626 | E7: =C7/C$11 -> 0.17786477 | F7: =C7/B7 -> 130.10935
A8: Inativos | B8: 22503 | C8: 1254586.3 | D8: =B8/B$11 -> 0.24169746 | E8: =C8/C$11 -> 0.095181226 | F8: =C8/B8 -> 55.751958
A9: Novos | B9: 21602 | C9: 1199262.1 | D9: =B9/B$11 -> 0.23202011 | E9: =C9/C$11 -> 0.090983966 | F9: =C9/B9 -> 55.516254
A10: Recorrentes | B10: 2789 | C10: 725355.04 | D10: =B10/B$11 -> 0.029955748 | E10: =C10/C$11 -> 0.055030236 | F10: =C10/B10 -> 260.0771
A11: Total | B11: =SUM(B5:B10) -> 93104 | C11: =SUM(C5:C10) -> 13181027 | D11: =B11/B11 -> 1 | E11: =C11/C11 -> 1 | F11: =C11/B11 -> 141.57316
A14: Indicadores derivados
A15: Taxa de recompra (clientes com 2+ pedidos) | B15: =INDEX(B5:B10,MATCH("Recorrentes",A5:A10,0))/B11 -> 0.029955748
A16: % da receita: Inativos de alto valor | B16: =INDEX(E5:E10,MATCH("Inativos de alto valor",A5:A10,0)) -> 0.28828989
A17: Clientes: Inativos de alto valor | B17: =INDEX(B5:B10,MATCH("Inativos de alto valor",A5:A10,0)) -> 13748
A18: Receita por cliente: Inativos de alto valor | B18: =INDEX(F5:F10,MATCH("Inativos de alto valor",A5:A10,0)) -> 276.4007

Sheet Vendedores
A1: Concentração de receita por vendedor
A2: Vendedores ordenados por receita e divididos em 5 grupos de igual tamanho (quintis). Azul = dado de entrada; preto = fórmula.
A4: Quintil (1 = maiores) | B4: Vendedores | C4: Receita (R$) | D4: % vendedores | E4: % Receita | F4: % receita acumulado
A5: 1 | B5: 589 | C5: 10834666 | D5: =B5/B$10 -> 0.2 | E5: =C5/C$10 -> 0.82198948 | F5: =SUM(E$5:E5) -> 0.82198948
A6: 2 | B6: 589 | C6: 1576670.3 | D6: =B6/B$10 -> 0.2 | E6: =C6/C$10 -> 0.11961665 | F6: =SUM(E$5:E6) -> 0.94160613
A7: 3 | B7: 589 | C7: 532432.4 | D7: =B7/B$10 -> 0.2 | E7: =C7/C$10 -> 0.040393848 | F7: =SUM(E$5:E7) -> 0.98199998
A8: 4 | B8: 589 | C8: 186749.14 | D8: =B8/B$10 -> 0.2 | E8: =C8/C$10 -> 0.014168026 | F8: =SUM(E$5:E8) -> 0.996168
A9: 5 | B9: 589 | C9: 50509.67 | D9: =B9/B$10 -> 0.2 | E9: =C9/C$10 -> 0.003831998 | F9: =SUM(E$5:E9) -> 1
A10: Total | B10: =SUM(B5:B9) -> 2945 | C10: =SUM(C5:C9) -> 13181027 | D10: =B10/B10 -> 1 | E10: =C10/C10 -> 1
A13: Os 20% maiores vendedores respondem por | B13: =E5 -> 0.82198948
A14: Os 40% menores vendedores respondem por | B14: =E8+E9 -> 0.018000024

Sheet Modelo_Risco
A1: Modelo de risco de atraso (resultados fora do tempo)
A2: Fonte: notebook 02. 12 janelas móveis (set/2017 a ago/2018), 74.206 pedidos. Azul = dado de entrada do notebook; preto = fórmula.
A3: 1. Taxa de atraso por folga do prazo (prazo prometido − tempo típico da rota)
A4: Folga do prazo | B4: Pedidos | C4: Atrasados | D4: Taxa de atraso | E4: % dos pedidos
A5: Folga de 0 dias ou menos (prazo menor que o típico) | B5: 1685 | C5: 512 | D5: =C5/B5 -> 0.30385757 | E5: =B5/B$10 -> 0.022707059
A6: Folga de 0 a 5 dias | B6: 9650 | C6: 1449 | D6: =C6/B6 -> 0.15015544 | E6: =B6/B$10 -> 0.13004339
A7: Folga de 5 a 10 dias | B7: 19620 | C7: 2179 | D7: =C7/B7 -> 0.11106014 | E7: =B7/B$10 -> 0.26439911
A8: Folga de 10 a 15 dias | B8: 21981 | C8: 1829 | D8: =C8/B8 -> 0.083208225 | E8: =B8/B$10 -> 0.29621594
A9: Folga acima de 15 dias | B9: 21270 | C9: 933 | D9: =C9/B9 -> 0.043864598 | E9: =B9/B$10 -> 0.2866345
A10: Total | B10: =SUM(B5:B9) -> 74206 | C10: =SUM(C5:C9) -> 6902 | D10: =C10/B10 -> 0.093011347 | E10: =B10/B10 -> 1
A11: Risco relativo: folga <= 0 dias vs folga > 15 dias | B11: =D5/D9 -> 6.9271709
A13: 2. Captura de atrasos ao sinalizar os X% de maior risco (média dos 12 meses)
A14: % de pedidos sinalizados | B14: Atrasos capturados | C14: Precisão (% dos sinalizados que atrasam) | D14: Lift vs. taxa-base
A15: 0.05 | B15: 0.1443 | C15: 0.2303 | D15: 2.892
A16: 0.1 | B16: 0.2684 | C16: 0.2221 | D16: 2.687
A17: 0.2 | B17: 0.4364 | C17: 0.1864 | D17: 2.183
A18: 0.3 | B18: 0.56 | C18: 0.1629 | D18: 1.867
A20: 3. Comparação de modelos (média dos 12 meses de teste; AUC 0,5 = acaso)
A21: Modelo | B21: AUC médio | C21: Desvio-padrão do AUC | D21: AUC do pior mês | E21: Captura no top 10% | F21: Lift no top 10%
A22: Logística: folga da rota (últimos 90 dias) | B22: 0.694 | C22: 0.049 | D22: 0.617 | E22: 0.2684 | F22: 2.687
A23: Logística: folga da rota (histórico) | B23: 0.675 | C23: 0.061 | D23: 0.59 | E23: 0.2449 | F23: 2.451
A24: Gradient boosting: atributos do pedido | B24: 0.65 | C24: 0.087 | D24: 0.444 | E24: 0.2331 | F24: 2.333
A25: Baseline: taxa histórica por UF | B25: 0.602 | C25: 0.09 | D25: 0.369 | E25: 0.1494 | F25: 1.496
A26: Gradient boosting: tudo | B26: 0.588 | C26: 0.066 | D26: 0.497 | E26: 0.1361 | F26: 1.362
A27: Logística: só prazo prometido | B27: 0.548 | C27: 0.103 | D27: 0.443 | E27: 0.1164 | F27: 1.165
A29: Linha destacada = modelo escolhido (regressão logística com folga da rota, janela de 90 dias).

Sheet Notas
A1: Notas, premissas e limitações
A2: Leia antes de usar os números.
A4: Tema | B4: Nota
A5: Fonte | B5: Brazilian E-Commerce Public Dataset by Olist (Kaggle, olistbr/brazilian-ecommerce). Dados reais, ~100 mil pedidos.
A6: Escopo | B6: Pedidos com status entregue e compra entre jan/2017 e ago/2018 (meses completos). Cliente = customer_unique_id. Receita = soma do preço dos itens, sem frete.
A7: Como esta planilha foi feita | B7: Os dados de base (células em AZUL) foram calculados em SQL/Python a partir da base original e colados como valores. Todo o resto (PRETO) é fórmula; vínculos entre abas aparecem em VERDE.
A8: Reprodução | B8: Scripts do projeto: carregar_banco.py, sql/01_views.sql, sql/02_consultas_negocio.sql, exportar_powerbi.py e notebooks 01 e 02. A planilha é regenerada por build_xlsx.py.
A9: Atraso | B9: Pedido entregue depois da data estimada informada ao cliente. 8 pedidos entregues sem data de entrega ficam fora das métricas de prazo.
A10: Nota Média | B10: Média das avaliações dos pedidos. Pedidos sem avaliação ficam fora do denominador.
A11: RFM | B11: Segmentação por regras de negócio (recência, valor e recorrência), não por clusters estatísticos. Como ~97% dos clientes compraram uma única vez, quintis de frequência não funcionam.
A12: Modelo de risco | B12: Usa só informações conhecidas na compra. Resultados vêm de validação temporal em 12 janelas móveis. A versão final (janela de 90 dias para o tempo típico da rota) foi escolhida depois de ver os resultados, o que gera leve otimismo.
A13: Limitação 1 | B13: Análise observacional: associação não é causalidade (atraso e nota baixa andam juntos, mas outros problemas também pesam na nota).
A14: Limitação 2 | B14: Receita não é lucro: a base não tem custo nem margem.
A15: Limitação 3 | B15: Janela de 20 meses de uma empresa em crescimento acelerado; tendências podem refletir a expansão e não comportamento estável.
... A17: Prioridades | B17: A coluna Prioridade da aba Recomendacoes é um julgamento do analista, não resultado de cálculo.
